aci/__init__.py
aci/aci.py
aci/components/__init__.py
aci/components/component.py
aci/components/drought.py
aci/components/precipitation.py
aci/components/sealevel.py
aci/components/temperature.py
aci/components/wind.py
aci/data/__init__.py
aci/data/psmsl_data.csv
aci/datasets.py
aci/request_copernicus_data.py
aci/request_sealevel_data.py
aci/utils.py
x_aci-0.0.1a4.dist-info/LICENSE
x_aci-0.0.1a4.dist-info/METADATA
x_aci-0.0.1a4.dist-info/WHEEL
x_aci-0.0.1a4.dist-info/RECORD
