Metadata-Version: 2.1
Name: x_aci
Version: 0.0.1a4
Summary: This package provides a way to calculate Actuarial Climate Indices based on meteorological data.
License: MIT
Author: XavierMilhaud
Requires-Python: >=3.12,<4.0
Classifier: License :: OSI Approved :: MIT License
Classifier: Programming Language :: Python :: 3
Classifier: Programming Language :: Python :: 3.12
Classifier: Programming Language :: Python :: 3.13
Requires-Dist: Bottleneck (>=1.4.2,<2.0.0)
Requires-Dist: cdsapi (>=0.7.4,<0.8.0)
Requires-Dist: dask (>=2024.10.0,<2025.0.0)
Requires-Dist: netCDF4 (>=1.7.2,<2.0.0)
Requires-Dist: pandas (>=2.2.3,<3.0.0)
Requires-Dist: psutil (>=6.1.0,<7.0.0)
Requires-Dist: requests (>=2.32.3,<3.0.0)
Requires-Dist: xarray (==2024.02.0)
